__init__.py
throttler.py
eko_throttler-0.2.0.dist-info/LICENSE
eko_throttler-0.2.0.dist-info/METADATA
eko_throttler-0.2.0.dist-info/WHEEL
eko_throttler-0.2.0.dist-info/top_level.txt
eko_throttler-0.2.0.dist-info/RECORD
