Metadata-Version: 2.1
Name: eko-throttler
Version: 0.2.0
Summary: Async implementation of a rate-limited lock object for Python 3.11.x
Author-email: Drix Holway <ekoteqmedia@gmail.com>
Classifier: Development Status :: 3 - Alpha
Classifier: Intended Audience :: Developers
Classifier: License :: OSI Approved :: MIT License
Classifier: Programming Language :: Python :: 3.11
Classifier: Operating System :: OS Independent
Requires-Python: >=3.11.0
License-File: LICENSE
